pwno-0.1.7.dist-info/METADATA
pwno-0.1.7.dist-info/WHEEL
pwno-0.1.7.dist-info/entry_points.txt
pwno-0.1.7.dist-info/licenses/LICENSE
pwno/__init__.py
pwno/cli/__init__.py
pwno/common/deprecate.py
pwno/context/__init__.py
pwno/context/abbreviation.py
pwno/context/context.py
pwno/context/gen_sh.py
pwno/gadget/__init__.py
pwno/gadget/gadget.py
pwno/helper/IO/__init__.py
pwno/helper/IO/cat.py
pwno/helper/IO/struct.py
pwno/helper/__init__.py
pwno/helper/utils.py
pwno/settings/__init__.py
pwno/settings/context.py
pwno/settings/general.py
pwno/typing/__init__.py
pwno/typing/pack.py
pwno/typing/types.py
pwno-0.1.7.dist-info/RECORD
