Metadata-Version: 2.1
Name: PwNo
Version: 0.1.7
Summary: Pwntools Extension that Just Works
Author-Email: MuelNova <n@ova.moe>
License: MIT
Requires-Python: >=3.10
Requires-Dist: pwntools>=4.12.0
Requires-Dist: pydantic>=2.8.2
Requires-Dist: setuptools>=71.1.0
Requires-Dist: sorcery>=0.2.2
Requires-Dist: ropper>=1.13.8
Requires-Dist: pydantic-settings>=2.6.1
Requires-Dist: toml>=0.10.2
